setup.py
gitxmlparser/LICENSE
gitxmlparser/README.md
gitxmlparser/__init__.py
gitxmlparser/gitxmlparser.py
gitxmlparser/requirements.txt
gitxmlparser.egg-info/PKG-INFO
gitxmlparser.egg-info/SOURCES.txt
gitxmlparser.egg-info/dependency_links.txt
gitxmlparser.egg-info/not-zip-safe
gitxmlparser.egg-info/requires.txt
gitxmlparser.egg-info/top_level.txt
gitxmlparser/bin/activate
gitxmlparser/bin/activate.csh
gitxmlparser/bin/activate.fish
gitxmlparser/bin/easy_install
gitxmlparser/bin/easy_install-2.7
gitxmlparser/bin/pip
gitxmlparser/bin/pip2
gitxmlparser/bin/pip2.7
gitxmlparser/bin/python
gitxmlparser/bin/python2
gitxmlparser/bin/python2.7
gitxmlparser/include/python2.7/ImDib.h
gitxmlparser/include/python2.7/ImPlatform.h
gitxmlparser/include/python2.7/Imaging.h
gitxmlparser/lib/python2.7/no-global-site-packages.txt
gitxmlparser/lib/python2.7/orig-prefix.txt
gitxmlparser/lib/python2.7/distutils/distutils.cfg
gitxmlparser/lib/python2.7/lib-dynload/Python-2.7.egg-info
gitxmlparser/lib/python2.7/lib-dynload/_bsddb.x86_64-linux-gnu.so
gitxmlparser/lib/python2.7/lib-dynload/_codecs_cn.x86_64-linux-gnu.so
gitxmlparser/lib/python2.7/lib-dynload/_codecs_hk.x86_64-linux-gnu.so
gitxmlparser/lib/python2.7/lib-dynload/_codecs_iso2022.x86_64-linux-gnu.so
gitxmlparser/lib/python2.7/lib-dynload/_codecs_jp.x86_64-linux-gnu.so
gitxmlparser/lib/python2.7/lib-dynload/_codecs_kr.x86_64-linux-gnu.so
gitxmlparser/lib/python2.7/lib-dynload/_codecs_tw.x86_64-linux-gnu.so
gitxmlparser/lib/python2.7/lib-dynload/_csv.x86_64-linux-gnu.so
gitxmlparser/lib/python2.7/lib-dynload/_ctypes.x86_64-linux-gnu.so
gitxmlparser/lib/python2.7/lib-dynload/_ctypes_test.x86_64-linux-gnu.so
gitxmlparser/lib/python2.7/lib-dynload/_curses.x86_64-linux-gnu.so
gitxmlparser/lib/python2.7/lib-dynload/_curses_panel.x86_64-linux-gnu.so
gitxmlparser/lib/python2.7/lib-dynload/_elementtree.x86_64-linux-gnu.so
gitxmlparser/lib/python2.7/lib-dynload/_hashlib.x86_64-linux-gnu.so
gitxmlparser/lib/python2.7/lib-dynload/_hotshot.x86_64-linux-gnu.so
gitxmlparser/lib/python2.7/lib-dynload/_json.x86_64-linux-gnu.so
gitxmlparser/lib/python2.7/lib-dynload/_lsprof.x86_64-linux-gnu.so
gitxmlparser/lib/python2.7/site-packages/pip-1.5.4.dist-info/DESCRIPTION.rst
gitxmlparser/lib/python2.7/site-packages/pip-1.5.4.dist-info/METADATA
gitxmlparser/lib/python2.7/site-packages/pip-1.5.4.dist-info/RECORD
gitxmlparser/lib/python2.7/site-packages/pip-1.5.4.dist-info/WHEEL
gitxmlparser/lib/python2.7/site-packages/pip-1.5.4.dist-info/entry_points.txt
gitxmlparser/lib/python2.7/site-packages/pip-1.5.4.dist-info/pydist.json
gitxmlparser/lib/python2.7/site-packages/pip-1.5.4.dist-info/top_level.txt
gitxmlparser/lib/python2.7/site-packages/requests-2.7.0.dist-info/DESCRIPTION.rst
gitxmlparser/lib/python2.7/site-packages/requests-2.7.0.dist-info/METADATA
gitxmlparser/lib/python2.7/site-packages/requests-2.7.0.dist-info/RECORD
gitxmlparser/lib/python2.7/site-packages/requests-2.7.0.dist-info/WHEEL
gitxmlparser/lib/python2.7/site-packages/requests-2.7.0.dist-info/metadata.json
gitxmlparser/lib/python2.7/site-packages/requests-2.7.0.dist-info/top_level.txt
gitxmlparser/lib/python2.7/site-packages/setuptools-2.2.dist-info/DESCRIPTION.rst
gitxmlparser/lib/python2.7/site-packages/setuptools-2.2.dist-info/METADATA
gitxmlparser/lib/python2.7/site-packages/setuptools-2.2.dist-info/RECORD
gitxmlparser/lib/python2.7/site-packages/setuptools-2.2.dist-info/WHEEL
gitxmlparser/lib/python2.7/site-packages/setuptools-2.2.dist-info/dependency_links.txt
gitxmlparser/lib/python2.7/site-packages/setuptools-2.2.dist-info/entry_points.txt
gitxmlparser/lib/python2.7/site-packages/setuptools-2.2.dist-info/pydist.json
gitxmlparser/lib/python2.7/site-packages/setuptools-2.2.dist-info/requires.txt.orig
gitxmlparser/lib/python2.7/site-packages/setuptools-2.2.dist-info/top_level.txt
gitxmlparser/lib/python2.7/site-packages/setuptools-2.2.dist-info/zip-safe
gitxmlparser/local/lib/python2.7/site-packages/pip-1.5.4.dist-info/DESCRIPTION.rst
gitxmlparser/local/lib/python2.7/site-packages/pip-1.5.4.dist-info/METADATA
gitxmlparser/local/lib/python2.7/site-packages/pip-1.5.4.dist-info/RECORD
gitxmlparser/local/lib/python2.7/site-packages/pip-1.5.4.dist-info/WHEEL
gitxmlparser/local/lib/python2.7/site-packages/pip-1.5.4.dist-info/entry_points.txt
gitxmlparser/local/lib/python2.7/site-packages/pip-1.5.4.dist-info/pydist.json
gitxmlparser/local/lib/python2.7/site-packages/pip-1.5.4.dist-info/top_level.txt
gitxmlparser/local/lib/python2.7/site-packages/requests-2.7.0.dist-info/DESCRIPTION.rst
gitxmlparser/local/lib/python2.7/site-packages/requests-2.7.0.dist-info/METADATA
gitxmlparser/local/lib/python2.7/site-packages/requests-2.7.0.dist-info/RECORD
gitxmlparser/local/lib/python2.7/site-packages/requests-2.7.0.dist-info/WHEEL
gitxmlparser/local/lib/python2.7/site-packages/requests-2.7.0.dist-info/metadata.json
gitxmlparser/local/lib/python2.7/site-packages/requests-2.7.0.dist-info/top_level.txt
gitxmlparser/local/lib/python2.7/site-packages/setuptools-2.2.dist-info/DESCRIPTION.rst
gitxmlparser/local/lib/python2.7/site-packages/setuptools-2.2.dist-info/METADATA
gitxmlparser/local/lib/python2.7/site-packages/setuptools-2.2.dist-info/RECORD
gitxmlparser/local/lib/python2.7/site-packages/setuptools-2.2.dist-info/WHEEL
gitxmlparser/local/lib/python2.7/site-packages/setuptools-2.2.dist-info/dependency_links.txt
gitxmlparser/local/lib/python2.7/site-packages/setuptools-2.2.dist-info/entry_points.txt
gitxmlparser/local/lib/python2.7/site-packages/setuptools-2.2.dist-info/pydist.json
gitxmlparser/local/lib/python2.7/site-packages/setuptools-2.2.dist-info/requires.txt.orig
gitxmlparser/local/lib/python2.7/site-packages/setuptools-2.2.dist-info/top_level.txt
gitxmlparser/local/lib/python2.7/site-packages/setuptools-2.2.dist-info/zip-safe
