Metadata-Version: 1.1
Name: gitxmlparser
Version: 0.1
Summary: Package made as an exercise for python pro's course python pratico.
Home-page: https://github.com/pedrohc/gitxmlparser
Author: Pedro Sampaio
Author-email: phcsss@gmail.com
License: BSD
Platform: UNKNOWN
Classifier: Development Status :: 4 - Beta
Classifier: Environment :: Web Environment
Classifier: Intended Audience :: Developers
Classifier: License :: OSI Approved :: BSD License
Classifier: Operating System :: OS Independent
Classifier: Programming Language :: Python
Classifier: Framework :: Paste
